faros/__init__.py
faros/client.py
faros/exceptions.py
faros/utils.py
tests/__init__.py
tests/test_client.py
tests/test_utils.py
faros-0.2.3.dist-info/LICENSE
faros-0.2.3.dist-info/METADATA
faros-0.2.3.dist-info/WHEEL
faros-0.2.3.dist-info/top_level.txt
faros-0.2.3.dist-info/RECORD
