Metadata-Version: 2.1
Name: faros
Version: 0.2.3
Summary: Faros API SDK
Home-page: https://github.com/faros-ai/faros-python-client
Author: Faros
Author-email: contact@faros.ai
License: UNKNOWN
Keywords: faros,api,graphql,sdk
Platform: UNKNOWN
Classifier: Programming Language :: Python :: 3
Classifier: Intended Audience :: Developers
Classifier: License :: OSI Approved :: Apache Software License
Classifier: Natural Language :: English
Classifier: Operating System :: OS Independent
Classifier: Topic :: Software Development :: Libraries :: Python Modules
Requires-Python: >=3.6
Requires-Dist: attrs
Requires-Dist: graphqlclient (>=0.2.4)
Requires-Dist: termcolor
Requires-Dist: datetime
Requires-Dist: time-window
